service_lookup/__init__.py
service_lookup/clean_processes.py
service_lookup/kubeconfig_setup.py
service_lookup/kubectl_service.py
service_lookup/lookup_cluster.py
service_lookup/main.py
service_lookup/uri_updater.py
service_lookup-0.2.7.dist-info/licenses/LICENSE
service_lookup-0.2.7.dist-info/METADATA
service_lookup-0.2.7.dist-info/WHEEL
service_lookup-0.2.7.dist-info/entry_points.txt
service_lookup-0.2.7.dist-info/top_level.txt
service_lookup-0.2.7.dist-info/RECORD
