Metadata-Version: 2.4
Name: service-lookup
Version: 0.2.7
Summary: Update host:port in YAML service URLs by service name and Kubernetes cluster
Author-email: Pavlos Smith <paulsmith4561@proton.me>
License-Expression: GPL-3.0
Project-URL: homepage, https://github.com/iByteABit256/service-lookup
Project-URL: repository, https://pypi.org/project/service-lookup/
Requires-Python: >=3.12
License-File: LICENSE
Requires-Dist: keyboard>=0.13.5
Requires-Dist: ruamel-yaml>=0.18.14
Dynamic: license-file
